{"words":[{"entry":{"id":1,"form":"a or kin"},"translations":[{"title":"PARTICLE","forms":["(emphasis, emotion or confirmation)"]}]},{"entry":{"id":2,"form":"akesi"},"translations":[{"title":"NOUN","forms":["non-cute animal; reptile, amphibian"]}]},{"entry":{"id":3,"form":"ala"},"translations":[{"title":"ADJECTIVE","forms":["no, not, zero"]}]},{"entry":{"id":4,"form":"alasa"},"translations":[{"title":"VERB","forms":["to hunt, forage"]}]},{"entry":{"id":5,"form":"ale or ali"},"translations":[{"title":"ADJECTIVE","forms":["all; abundant, countless, bountiful, every, plentiful"]},{"title":"NOUN","forms":["abundance, everything, life, universe"]},{"title":"NUMBER","forms":["100"]}]},{"entry":{"id":6,"form":"anpa"},"translations":[{"title":"ADJECTIVE","forms":["bowing down, downward, humble, lowly, dependent"]}]},{"entry":{"id":7,"form":"ante"},"translations":[{"title":"ADJECTIVE","forms":["different, altered, changed, other"]}]},{"entry":{"id":8,"form":"anu"},"translations":[{"title":"PARTICLE","forms":["or"]}]},{"entry":{"id":9,"form":"awen"},"translations":[{"title":"ADJECTIVE","forms":["enduring, kept, protected, safe, waiting, staying"]},{"title":"PRE-VERB","forms":["to continue to"]}]},{"entry":{"id":10,"form":"e"},"translations":[{"title":"PARTICLE","forms":["(before the direct object)"]}]},{"entry":{"id":11,"form":"en"},"translations":[{"title":"PARTICLE","forms":["(between multiple subjects)"]}]},{"entry":{"id":12,"form":"esun"},"translations":[{"title":"NOUN","forms":["market, shop, fair, bazaar, business transaction"]}]},{"entry":{"id":13,"form":"ijo"},"translations":[{"title":"NOUN","forms":["thing, phenomenon, object, matter"]}]},{"entry":{"id":14,"form":"ike"},"translations":[{"title":"ADJECTIVE","forms":["bad, negative; non-essential, irrelevant"]}]},{"entry":{"id":15,"form":"ilo"},"translations":[{"title":"NOUN","forms":["tool, implement, machine, device"]}]},{"entry":{"id":16,"form":"insa"},"translations":[{"title":"NOUN","forms":["centre, content, inside, between; internal organ, stomach"]}]},{"entry":{"id":17,"form":"jaki"},"translations":[{"title":"ADJECTIVE","forms":["disgusting, obscene, sickly, toxic, unclean, unsanitary"]}]},{"entry":{"id":18,"form":"jan"},"translations":[{"title":"NOUN","forms":["human being, person, somebody"]}]},{"entry":{"id":19,"form":"jelo"},"translations":[{"title":"ADJECTIVE","forms":["yellow, yellowish"]}]},{"entry":{"id":20,"form":"jo"},"translations":[{"title":"VERB","forms":["to have, carry, contain, hold"]}]},{"entry":{"id":21,"form":"kala"},"translations":[{"title":"NOUN","forms":["fish, marine animal, sea creature"]}]},{"entry":{"id":22,"form":"kalama"},"translations":[{"title":"VERB","forms":["to produce a sound; recite, utter aloud"]}]},{"entry":{"id":23,"form":"kama"},"translations":[{"title":"ADJECTIVE","forms":["arriving, coming, future, summoned"]},{"title":"PRE-VERB","forms":["to become, manage to, succeed in"]}]},{"entry":{"id":24,"form":"kasi"},"translations":[{"title":"NOUN","forms":["plant, vegetation; herb, leaf"]}]},{"entry":{"id":25,"form":"ken"},"translations":[{"title":"PRE-VERB","forms":["to be able to, be allowed to, can, may"]},{"title":"ADJECTIVE","forms":["possible"]}]},{"entry":{"id":26,"form":"kepeken"},"translations":[{"title":"PREPOSITION","forms":["to use, with, by means of"]}]},{"entry":{"id":27,"form":"kili"},"translations":[{"title":"NOUN","forms":["fruit, vegetable, mushroom"]}]},{"entry":{"id":28,"form":"kiwen"},"translations":[{"title":"NOUN","forms":["hard object, metal, rock, stone"]}]},{"entry":{"id":29,"form":"ko"},"translations":[{"title":"NOUN","forms":["clay, clinging form, dough, semi-solid, paste, powder"]}]},{"entry":{"id":30,"form":"kon"},"translations":[{"title":"NOUN","forms":["air, breath; essence, spirit; hidden reality, unseen agent"]}]},{"entry":{"id":31,"form":"kule"},"translations":[{"title":"ADJECTIVE","forms":["colourful, pigmented, painted"]}]},{"entry":{"id":32,"form":"kulupu"},"translations":[{"title":"NOUN","forms":["community, company, group, nation, society, tribe"]}]},{"entry":{"id":33,"form":"kute"},"translations":[{"title":"NOUN","forms":["ear"]},{"title":"VERB","forms":["to hear, listen; pay attention to, obey"]}]},{"entry":{"id":34,"form":"la"},"translations":[{"title":"PARTICLE","forms":["(between the context phrase and the main sentence)"]}]},{"entry":{"id":35,"form":"lape"},"translations":[{"title":"ADJECTIVE","forms":["sleeping, resting"]}]},{"entry":{"id":36,"form":"laso"},"translations":[{"title":"ADJECTIVE","forms":["blue, green"]}]},{"entry":{"id":37,"form":"lawa"},"translations":[{"title":"NOUN","forms":["head, mind"]},{"title":"VERB","forms":["to control, direct, guide, lead, own, plan, regulate, rule"]}]},{"entry":{"id":38,"form":"len"},"translations":[{"title":"NOUN","forms":["cloth, clothing, fabric, textile; cover, layer of privacy"]}]},{"entry":{"id":39,"form":"lete"},"translations":[{"title":"ADJECTIVE","forms":["cold, cool; uncooked, raw"]}]},{"entry":{"id":40,"form":"li"},"translations":[{"title":"PARTICLE","forms":["(between any subject except mi alone or sina alone and its verb; also to introduce a new verb for the same subject)"]}]},{"entry":{"id":41,"form":"lili"},"translations":[{"title":"ADJECTIVE","forms":["little, small, short; few; a bit; young"]}]},{"entry":{"id":42,"form":"linja"},"translations":[{"title":"NOUN","forms":["long and flexible thing; cord, hair, rope, thread, yarn"]}]},{"entry":{"id":43,"form":"lipu"},"translations":[{"title":"NOUN","forms":["flat object; book, document, card, paper, record, website"]}]},{"entry":{"id":44,"form":"loje"},"translations":[{"title":"ADJECTIVE","forms":["red, reddish"]}]},{"entry":{"id":45,"form":"lon"},"translations":[{"title":"PREPOSITION","forms":["located at, present at, real, true, existing"]}]},{"entry":{"id":46,"form":"luka"},"translations":[{"title":"NOUN","forms":["arm, hand, tactile organ"]},{"title":"NUMBER","forms":["five"]}]},{"entry":{"id":47,"form":"lukin or oko"},"translations":[{"title":"NOUN","forms":["eye"]},{"title":"VERB","forms":["to look at, see, examine, observe, read, watch"]},{"title":"PRE-VERB","forms":["to seek, look for, try to"]}]},{"entry":{"id":48,"form":"lupa"},"translations":[{"title":"NOUN","forms":["door, hole, orifice, window"]}]},{"entry":{"id":49,"form":"ma"},"translations":[{"title":"NOUN","forms":["earth, land; outdoors, world; country, territory; soil"]}]},{"entry":{"id":50,"form":"mama"},"translations":[{"title":"NOUN","forms":["parent, ancestor; creator, originator; caretaker, sustainer"]}]},{"entry":{"id":51,"form":"mani"},"translations":[{"title":"NOUN","forms":["money, cash, savings, wealth; large domesticated animal"]}]},{"entry":{"id":52,"form":"meli"},"translations":[{"title":"NOUN","forms":["woman, female, feminine person; wife"]}]},{"entry":{"id":53,"form":"mi"},"translations":[{"title":"NOUN","forms":["I, me, we, us"]}]},{"entry":{"id":54,"form":"mije"},"translations":[{"title":"NOUN","forms":["man, male, masculine person; husband"]}]},{"entry":{"id":55,"form":"moku"},"translations":[{"title":"VERB","forms":["to eat, drink, consume, swallow, ingest"]}]},{"entry":{"id":56,"form":"moli"},"translations":[{"title":"ADJECTIVE","forms":["dead, dying"]}]},{"entry":{"id":57,"form":"monsi"},"translations":[{"title":"NOUN","forms":["back, behind, rear"]}]},{"entry":{"id":58,"form":"mu"},"translations":[{"title":"PARTICLE","forms":["(animal noise or communication)"]}]},{"entry":{"id":59,"form":"mun"},"translations":[{"title":"NOUN","forms":["moon, night sky object, star"]}]},{"entry":{"id":60,"form":"musi"},"translations":[{"title":"ADJECTIVE","forms":["artistic, entertaining, frivolous, playful, recreational"]}]},{"entry":{"id":61,"form":"mute"},"translations":[{"title":"ADJECTIVE","forms":["many, a lot, more, much, several, very"]},{"title":"NOUN","forms":["quantity"]}]},{"entry":{"id":62,"form":"nanpa"},"translations":[{"title":"PARTICLE","forms":["-th (ordinal number)"]},{"title":"NOUN","forms":["numbers"]}]},{"entry":{"id":63,"form":"nasa"},"translations":[{"title":"ADJECTIVE","forms":["unusual, strange; foolish, crazy; drunk, intoxicated"]}]},{"entry":{"id":64,"form":"nasin"},"translations":[{"title":"NOUN","forms":["way, custom, doctrine, method, path, road"]}]},{"entry":{"id":65,"form":"nena"},"translations":[{"title":"NOUN","forms":["bump, button, hill, mountain, nose, protuberance"]}]},{"entry":{"id":66,"form":"ni"},"translations":[{"title":"ADJECTIVE","forms":["that, this"]}]},{"entry":{"id":67,"form":"nimi"},"translations":[{"title":"NOUN","forms":["name, word"]}]},{"entry":{"id":68,"form":"noka"},"translations":[{"title":"NOUN","forms":["foot, leg, organ of locomotion; bottom, lower part"]}]},{"entry":{"id":69,"form":"o"},"translations":[{"title":"PARTICLE","forms":["hey! O! (vocative or imperative)"]}]},{"entry":{"id":70,"form":"olin"},"translations":[{"title":"VERB","forms":["to love, have compassion for, respect, show affection to"]}]},{"entry":{"id":71,"form":"ona"},"translations":[{"title":"NOUN","forms":["he, she, it, they"]}]},{"entry":{"id":72,"form":"open"},"translations":[{"title":"VERB","forms":["to begin, start; open; turn on"]}]},{"entry":{"id":73,"form":"pakala"},"translations":[{"title":"ADJECTIVE","forms":["botched, broken, damaged, harmed, messed up"]}]},{"entry":{"id":74,"form":"pali"},"translations":[{"title":"VERB","forms":["to do, take action on, work on; build, make, prepare"]}]},{"entry":{"id":75,"form":"palisa"},"translations":[{"title":"NOUN","forms":["long hard thing; branch, rod, stick"]}]},{"entry":{"id":76,"form":"pan"},"translations":[{"title":"NOUN","forms":["cereal, grain; barley, corn, oat, rice, wheat; bread, pasta"]}]},{"entry":{"id":77,"form":"pana"},"translations":[{"title":"VERB","forms":["to give, send, emit, provide, put, release"]}]},{"entry":{"id":78,"form":"pi"},"translations":[{"title":"PARTICLE","forms":["of"]}]},{"entry":{"id":79,"form":"pilin"},"translations":[{"title":"NOUN","forms":["heart (physical or emotional)"]},{"title":"ADJECTIVE","forms":["feeling (an emotion, a direct experience)"]}]},{"entry":{"id":80,"form":"pimeja"},"translations":[{"title":"ADJECTIVE","forms":["black, dark, unlit"]}]},{"entry":{"id":81,"form":"pini"},"translations":[{"title":"ADJECTIVE","forms":["ago, completed, ended, finished, past"]}]},{"entry":{"id":82,"form":"pipi"},"translations":[{"title":"NOUN","forms":["bug, insect, ant, spider"]}]},{"entry":{"id":83,"form":"poka"},"translations":[{"title":"NOUN","forms":["hip, side; next to, nearby, vicinity"]}]},{"entry":{"id":84,"form":"poki"},"translations":[{"title":"NOUN","forms":["container, bag, bowl, box, cup, cupboard, drawer, vessel"]}]},{"entry":{"id":85,"form":"pona"},"translations":[{"title":"ADJECTIVE","forms":["good, positive, useful; friendly, peaceful; simple"]}]},{"entry":{"id":86,"form":"pu"},"translations":[{"title":"ADJECTIVE","forms":["interacting with the Toki Pona book"]}]},{"entry":{"id":87,"form":"sama"},"translations":[{"title":"ADJECTIVE","forms":["same, similar; each other; sibling, peer, fellow"]},{"title":"PREPOSITION","forms":["as, like"]}]},{"entry":{"id":88,"form":"seli"},"translations":[{"title":"ADJECTIVE","forms":["fire; cooking element, chemical reaction, heat source"]}]},{"entry":{"id":89,"form":"selo"},"translations":[{"title":"NOUN","forms":["outer form, outer layer; bark, peel, shell, skin; boundary"]}]},{"entry":{"id":90,"form":"seme"},"translations":[{"title":"PARTICLE","forms":["what? which?"]}]},{"entry":{"id":91,"form":"sewi"},"translations":[{"title":"NOUN","forms":["area above, highest part, something elevated"]},{"title":"ADJECTIVE","forms":["awe-inspiring, divine, sacred, supernatural"]}]},{"entry":{"id":92,"form":"sijelo"},"translations":[{"title":"NOUN","forms":["body (of person or animal), physical state, torso"]}]},{"entry":{"id":93,"form":"sike"},"translations":[{"title":"NOUN","forms":["round or circular thing; ball, circle, cycle, sphere, wheel"]},{"title":"ADJECTIVE","forms":["of one year"]}]},{"entry":{"id":94,"form":"sin or namako"},"translations":[{"title":"ADJECTIVE","forms":["new, fresh; additional, another, extra"]}]},{"entry":{"id":95,"form":"sina"},"translations":[{"title":"NOUN","forms":["you"]}]},{"entry":{"id":96,"form":"sinpin"},"translations":[{"title":"NOUN","forms":["face, foremost, front, wall"]}]},{"entry":{"id":97,"form":"sitelen"},"translations":[{"title":"NOUN","forms":["image, picture, representation, symbol, mark, writing"]}]},{"entry":{"id":98,"form":"sona"},"translations":[{"title":"VERB","forms":["to know, be skilled in, be wise about, have information on"]},{"title":"PRE-VERB","forms":["to know how to"]}]},{"entry":{"id":99,"form":"soweli"},"translations":[{"title":"NOUN","forms":["animal, beast, land mammal"]}]},{"entry":{"id":100,"form":"suli"},"translations":[{"title":"ADJECTIVE","forms":["big, heavy, large, long, tall; important; adult"]}]},{"entry":{"id":101,"form":"suno"},"translations":[{"title":"NOUN","forms":["sun; light, brightness, glow, radiance, shine; light source"]}]},{"entry":{"id":102,"form":"supa"},"translations":[{"title":"NOUN","forms":["horizontal surface, thing to put or rest something on"]}]},{"entry":{"id":103,"form":"suwi"},"translations":[{"title":"ADJECTIVE","forms":["sweet, fragrant; cute, innocent, adorable"]}]},{"entry":{"id":104,"form":"tan"},"translations":[{"title":"PREPOSITION","forms":["by, from, because of"]}]},{"entry":{"id":105,"form":"taso"},"translations":[{"title":"PARTICLE","forms":["but, however"]},{"title":"ADJECTIVE","forms":["only"]}]},{"entry":{"id":106,"form":"tawa"},"translations":[{"title":"PREPOSITION","forms":["going to, toward; for; from the perspective of"]},{"title":"ADJECTIVE","forms":["moving"]}]},{"entry":{"id":107,"form":"telo"},"translations":[{"title":"NOUN","forms":["water, liquid, fluid, wet substance; beverage"]}]},{"entry":{"id":108,"form":"tenpo"},"translations":[{"title":"NOUN","forms":["time, duration, moment, occasion, period, situation"]}]},{"entry":{"id":109,"form":"toki"},"translations":[{"title":"VERB","forms":["to communicate, say, speak, say, talk, use language, think"]}]},{"entry":{"id":110,"form":"tomo"},"translations":[{"title":"NOUN","forms":["indoor space; building, home, house, room"]}]},{"entry":{"id":111,"form":"tu"},"translations":[{"title":"NUMBER","forms":["two"]}]},{"entry":{"id":112,"form":"unpa"},"translations":[{"title":"VERB","forms":["to have sexual or marital relations with"]}]},{"entry":{"id":113,"form":"uta"},"translations":[{"title":"NOUN","forms":["mouth, lips, oral cavity, jaw"]}]},{"entry":{"id":114,"form":"utala"},"translations":[{"title":"VERB","forms":["to battle, challenge, compete against, struggle against"]}]},{"entry":{"id":115,"form":"walo"},"translations":[{"title":"ADJECTIVE","forms":["white, whitish; light-coloured, pale"]}]},{"entry":{"id":116,"form":"wan"},"translations":[{"title":"ADJECTIVE","forms":["unique, united"]},{"title":"NUMBER","forms":["one"]}]},{"entry":{"id":117,"form":"waso"},"translations":[{"title":"NOUN","forms":["bird, flying creature, winged animal"]}]},{"entry":{"id":118,"form":"wawa"},"translations":[{"title":"ADJECTIVE","forms":["strong, powerful; confident, sure; energetic, intense"]}]},{"entry":{"id":119,"form":"weka"},"translations":[{"title":"ADJECTIVE","forms":["absent, away, ignored"]}]},{"entry":{"id":120,"form":"wile"},"translations":[{"title":"PRE-VERB","forms":["must, need, require, should, want, wish"]}]}]}